{
  "AWSTemplateFormatVersion": "2010-09-09",
  "Description": "The AWS CloudFormation template for this Serverless application",
  "Resources": {
    "ServerlessDeploymentBucket": {
      "Type": "AWS::S3::Bucket"
    },
    "IamRoleLambdaExecution": {
      "Type": "AWS::IAM::Role",
      "Properties": {
        "AssumeRolePolicyDocument": {
          "Version": "2012-10-17",
          "Statement": [
            {
              "Effect": "Allow",
              "Principal": {
                "Service": [
                  "lambda.amazonaws.com"
                ]
              },
              "Action": [
                "sts:AssumeRole"
              ]
            }
          ]
        },
        "Path": "/",
        "RoleName": {
          "Fn::Join": [
            "-",
            [
              "serverless-brewerydb-for-breweryup-app",
              "v2",
              "us-west-1",
              "lambdaRole"
            ]
          ]
        }
      }
    },
    "IamPolicyLambdaExecution": {
      "Type": "AWS::IAM::Policy",
      "DependsOn": [
        "IamRoleLambdaExecution"
      ],
      "Properties": {
        "PolicyName": {
          "Fn::Join": [
            "-",
            [
              "v2",
              "serverless-brewerydb-for-breweryup-app",
              "lambda"
            ]
          ]
        },
        "PolicyDocument": {
          "Version": "2012-10-17",
          "Statement": [
            {
              "Effect": "Allow",
              "Action": [
                "logs:CreateLogStream",
                "logs:PutLogEvents"
              ],
              "Resource": [
                {
                  "Fn::Join": [
                    ":",
                    [
                      {
                        "Fn::GetAtt": [
                          "GetOneLogGroup",
                          "Arn"
                        ]
                      },
                      "*"
                    ]
                  ]
                },
                {
                  "Fn::Join": [
                    ":",
                    [
                      {
                        "Fn::GetAtt": [
                          "GetAllLogGroup",
                          "Arn"
                        ]
                      },
                      "*"
                    ]
                  ]
                }
              ]
            },
            {
              "Effect": "Allow",
              "Action": [
                "s3:*",
                "cloudwatch:*"
              ],
              "Resource": "*"
            }
          ]
        },
        "Roles": [
          {
            "Ref": "IamRoleLambdaExecution"
          }
        ]
      }
    },
    "GetOneLogGroup": {
      "Type": "AWS::Logs::LogGroup",
      "Properties": {
        "LogGroupName": "/aws/lambda/serverless-brewerydb-for-breweryup-app-v2-getOne"
      }
    },
    "GetAllLogGroup": {
      "Type": "AWS::Logs::LogGroup",
      "Properties": {
        "LogGroupName": "/aws/lambda/serverless-brewerydb-for-breweryup-app-v2-getAll"
      }
    },
    "GetOneLambdaFunction": {
      "Type": "AWS::Lambda::Function",
      "Properties": {
        "Code": {
          "S3Bucket": {
            "Ref": "ServerlessDeploymentBucket"
          },
          "S3Key": "serverless/serverless-brewerydb-for-breweryup-app/v2/1486874552913-2017-02-12T04:42:32.913Z/serverless-brewerydb-for-breweryup-app-v2-getOne.zip"
        },
        "FunctionName": "serverless-brewerydb-for-breweryup-app-v2-getOne",
        "Handler": "_optimize/serverless-brewerydb-for-breweryup-app-v2-getOne/handlers/beers/getBeer.getBeer",
        "MemorySize": 1024,
        "Role": {
          "Fn::GetAtt": [
            "IamRoleLambdaExecution",
            "Arn"
          ]
        },
        "Runtime": "nodejs4.3",
        "Timeout": 6
      },
      "DependsOn": [
        "IamPolicyLambdaExecution",
        "IamRoleLambdaExecution"
      ]
    },
    "GetOneLambdaVersiongANkUULSFXTVajACJsDneWX2es5dPpVH6Bg9mI09v8": {
      "Type": "AWS::Lambda::Version",
      "DeletionPolicy": "Retain",
      "Properties": {
        "FunctionName": {
          "Ref": "GetOneLambdaFunction"
        },
        "CodeSha256": "gANkUULSFXT/VajACJsDneWX2es5dPpVH6Bg9mI09v8="
      }
    },
    "GetAllLambdaFunction": {
      "Type": "AWS::Lambda::Function",
      "Properties": {
        "Code": {
          "S3Bucket": {
            "Ref": "ServerlessDeploymentBucket"
          },
          "S3Key": "serverless/serverless-brewerydb-for-breweryup-app/v2/1486874552913-2017-02-12T04:42:32.913Z/serverless-brewerydb-for-breweryup-app-v2-getAll.zip"
        },
        "FunctionName": "serverless-brewerydb-for-breweryup-app-v2-getAll",
        "Handler": "_optimize/serverless-brewerydb-for-breweryup-app-v2-getAll/handlers/beers/getBeers.getBeers",
        "MemorySize": 1024,
        "Role": {
          "Fn::GetAtt": [
            "IamRoleLambdaExecution",
            "Arn"
          ]
        },
        "Runtime": "nodejs4.3",
        "Timeout": 6
      },
      "DependsOn": [
        "IamPolicyLambdaExecution",
        "IamRoleLambdaExecution"
      ]
    },
    "GetAllLambdaVersionuBh2QCn69uklMiYyK6fY9eqy6CMAgXSCqKY889rug": {
      "Type": "AWS::Lambda::Version",
      "DeletionPolicy": "Retain",
      "Properties": {
        "FunctionName": {
          "Ref": "GetAllLambdaFunction"
        },
        "CodeSha256": "uBh2QCn6/9uklMiYyK6fY9eqy6CMAgX+SCqKY889rug="
      }
    },
    "ApiGatewayRestApi": {
      "Type": "AWS::ApiGateway::RestApi",
      "Properties": {
        "Name": "v2-serverless-brewerydb-for-breweryup-app"
      }
    },
    "ApiGatewayResourceBeers": {
      "Type": "AWS::ApiGateway::Resource",
      "Properties": {
        "ParentId": {
          "Fn::GetAtt": [
            "ApiGatewayRestApi",
            "RootResourceId"
          ]
        },
        "PathPart": "beers",
        "RestApiId": {
          "Ref": "ApiGatewayRestApi"
        }
      }
    },
    "ApiGatewayResourceBeersIdVar": {
      "Type": "AWS::ApiGateway::Resource",
      "Properties": {
        "ParentId": {
          "Ref": "ApiGatewayResourceBeers"
        },
        "PathPart": "{id}",
        "RestApiId": {
          "Ref": "ApiGatewayRestApi"
        }
      }
    },
    "ApiGatewayMethodBeersIdVarOptions": {
      "Type": "AWS::ApiGateway::Method",
      "Properties": {
        "AuthorizationType": "NONE",
        "HttpMethod": "OPTIONS",
        "MethodResponses": [
          {
            "StatusCode": "200",
            "ResponseParameters": {
              "method.response.header.Access-Control-Allow-Origin": true,
              "method.response.header.Access-Control-Allow-Headers": true,
              "method.response.header.Access-Control-Allow-Methods": true,
              "method.response.header.Access-Control-Allow-Credentials": true
            },
            "ResponseModels": {}
          }
        ],
        "RequestParameters": {},
        "Integration": {
          "Type": "MOCK",
          "RequestTemplates": {
            "application/json": "{statusCode:200}"
          },
          "IntegrationResponses": [
            {
              "StatusCode": "200",
              "ResponseParameters": {
                "method.response.header.Access-Control-Allow-Origin": "'*'",
                "method.response.header.Access-Control-Allow-Headers": "'Content-Type,X-Amz-Date,Authorization,X-Api-Key,X-Amz-Security-Token'",
                "method.response.header.Access-Control-Allow-Methods": "'OPTIONS,GET'",
                "method.response.header.Access-Control-Allow-Credentials": "'false'"
              },
              "ResponseTemplates": {
                "application/json": ""
              }
            }
          ]
        },
        "ResourceId": {
          "Ref": "ApiGatewayResourceBeersIdVar"
        },
        "RestApiId": {
          "Ref": "ApiGatewayRestApi"
        }
      }
    },
    "ApiGatewayMethodBeersOptions": {
      "Type": "AWS::ApiGateway::Method",
      "Properties": {
        "AuthorizationType": "NONE",
        "HttpMethod": "OPTIONS",
        "MethodResponses": [
          {
            "StatusCode": "200",
            "ResponseParameters": {
              "method.response.header.Access-Control-Allow-Origin": true,
              "method.response.header.Access-Control-Allow-Headers": true,
              "method.response.header.Access-Control-Allow-Methods": true,
              "method.response.header.Access-Control-Allow-Credentials": true
            },
            "ResponseModels": {}
          }
        ],
        "RequestParameters": {},
        "Integration": {
          "Type": "MOCK",
          "RequestTemplates": {
            "application/json": "{statusCode:200}"
          },
          "IntegrationResponses": [
            {
              "StatusCode": "200",
              "ResponseParameters": {
                "method.response.header.Access-Control-Allow-Origin": "'*'",
                "method.response.header.Access-Control-Allow-Headers": "'Content-Type,X-Amz-Date,Authorization,X-Api-Key,X-Amz-Security-Token'",
                "method.response.header.Access-Control-Allow-Methods": "'OPTIONS,GET'",
                "method.response.header.Access-Control-Allow-Credentials": "'false'"
              },
              "ResponseTemplates": {
                "application/json": ""
              }
            }
          ]
        },
        "ResourceId": {
          "Ref": "ApiGatewayResourceBeers"
        },
        "RestApiId": {
          "Ref": "ApiGatewayRestApi"
        }
      }
    },
    "ApiGatewayMethodBeersIdVarGet": {
      "Type": "AWS::ApiGateway::Method",
      "Properties": {
        "HttpMethod": "GET",
        "RequestParameters": {},
        "ResourceId": {
          "Ref": "ApiGatewayResourceBeersIdVar"
        },
        "RestApiId": {
          "Ref": "ApiGatewayRestApi"
        },
        "AuthorizationType": "NONE",
        "Integration": {
          "IntegrationHttpMethod": "POST",
          "Type": "AWS",
          "Uri": {
            "Fn::Join": [
              "",
              [
                "arn:aws:apigateway:",
                {
                  "Ref": "AWS::Region"
                },
                ":lambda:path/2015-03-31/functions/",
                {
                  "Fn::GetAtt": [
                    "GetOneLambdaFunction",
                    "Arn"
                  ]
                },
                "/invocations"
              ]
            ]
          },
          "PassthroughBehavior": "NEVER",
          "RequestTemplates": {
            "application/json": "\n    #set( $body = $input.json(\"$\") )\n\n    \n  #define( $loop )\n    {\n    #foreach($key in $map.keySet())\n        #set( $k = $util.escapeJavaScript($key) )\n        #set( $v = $util.escapeJavaScript($map.get($key)).replaceAll(\"\\\\'\", \"'\") )\n        \"$k\":\n          \"$v\"\n          #if( $foreach.hasNext ) , #end\n    #end\n    }\n  #end\n\n  {\n    \"body\": $body,\n    \"method\": \"$context.httpMethod\",\n    \"principalId\": \"$context.authorizer.principalId\",\n    \"stage\": \"$context.stage\",\n\n    \"cognitoPoolClaims\" : {\n       \n       \"sub\": \"$context.authorizer.claims.sub\"\n    },\n\n    #set( $map = $input.params().header )\n    \"headers\": $loop,\n\n    #set( $map = $input.params().querystring )\n    \"query\": $loop,\n\n    #set( $map = $input.params().path )\n    \"path\": $loop,\n\n    #set( $map = $context.identity )\n    \"identity\": $loop,\n\n    #set( $map = $stageVariables )\n    \"stageVariables\": $loop\n  }\n\n  ",
            "application/x-www-form-urlencoded": "\n    #define( $body )\n      {\n      #foreach( $token in $input.path('$').split('&') )\n        #set( $keyVal = $token.split('=') )\n        #set( $keyValSize = $keyVal.size() )\n        #if( $keyValSize >= 1 )\n          #set( $key = $util.escapeJavaScript($util.urlDecode($keyVal[0])) )\n          #if( $keyValSize >= 2 )\n            #set($val = $util.escapeJavaScript($util.urlDecode($keyVal[1])).replaceAll(\"\\\\'\",\"'\"))\n          #else\n            #set( $val = '' )\n          #end\n          \"$key\": \"$val\"#if($foreach.hasNext),#end\n        #end\n      #end\n      }\n    #end\n\n    \n  #define( $loop )\n    {\n    #foreach($key in $map.keySet())\n        #set( $k = $util.escapeJavaScript($key) )\n        #set( $v = $util.escapeJavaScript($map.get($key)).replaceAll(\"\\\\'\", \"'\") )\n        \"$k\":\n          \"$v\"\n          #if( $foreach.hasNext ) , #end\n    #end\n    }\n  #end\n\n  {\n    \"body\": $body,\n    \"method\": \"$context.httpMethod\",\n    \"principalId\": \"$context.authorizer.principalId\",\n    \"stage\": \"$context.stage\",\n\n    \"cognitoPoolClaims\" : {\n       \n       \"sub\": \"$context.authorizer.claims.sub\"\n    },\n\n    #set( $map = $input.params().header )\n    \"headers\": $loop,\n\n    #set( $map = $input.params().querystring )\n    \"query\": $loop,\n\n    #set( $map = $input.params().path )\n    \"path\": $loop,\n\n    #set( $map = $context.identity )\n    \"identity\": $loop,\n\n    #set( $map = $stageVariables )\n    \"stageVariables\": $loop\n  }\n\n  "
          },
          "IntegrationResponses": [
            {
              "StatusCode": 200,
              "SelectionPattern": "",
              "ResponseParameters": {
                "method.response.header.Access-Control-Allow-Origin": "'*'"
              },
              "ResponseTemplates": {}
            },
            {
              "StatusCode": 400,
              "SelectionPattern": "[\\s\\S]*\\[400\\][\\s\\S]*",
              "ResponseParameters": {
                "method.response.header.Access-Control-Allow-Origin": "'*'"
              },
              "ResponseTemplates": {}
            },
            {
              "StatusCode": 401,
              "SelectionPattern": "[\\s\\S]*\\[401\\][\\s\\S]*",
              "ResponseParameters": {
                "method.response.header.Access-Control-Allow-Origin": "'*'"
              },
              "ResponseTemplates": {}
            },
            {
              "StatusCode": 403,
              "SelectionPattern": "[\\s\\S]*\\[403\\][\\s\\S]*",
              "ResponseParameters": {
                "method.response.header.Access-Control-Allow-Origin": "'*'"
              },
              "ResponseTemplates": {}
            },
            {
              "StatusCode": 404,
              "SelectionPattern": "[\\s\\S]*\\[404\\][\\s\\S]*",
              "ResponseParameters": {
                "method.response.header.Access-Control-Allow-Origin": "'*'"
              },
              "ResponseTemplates": {}
            },
            {
              "StatusCode": 422,
              "SelectionPattern": "[\\s\\S]*\\[422\\][\\s\\S]*",
              "ResponseParameters": {
                "method.response.header.Access-Control-Allow-Origin": "'*'"
              },
              "ResponseTemplates": {}
            },
            {
              "StatusCode": 500,
              "SelectionPattern": "[\\s\\S]*(Process\\s?exited\\s?before\\s?completing\\s?request|\\[500\\])[\\s\\S]*",
              "ResponseParameters": {
                "method.response.header.Access-Control-Allow-Origin": "'*'"
              },
              "ResponseTemplates": {}
            },
            {
              "StatusCode": 502,
              "SelectionPattern": "[\\s\\S]*\\[502\\][\\s\\S]*",
              "ResponseParameters": {
                "method.response.header.Access-Control-Allow-Origin": "'*'"
              },
              "ResponseTemplates": {}
            },
            {
              "StatusCode": 504,
              "SelectionPattern": "[\\s\\S]*\\[504\\][\\s\\S]*",
              "ResponseParameters": {
                "method.response.header.Access-Control-Allow-Origin": "'*'"
              },
              "ResponseTemplates": {}
            }
          ]
        },
        "MethodResponses": [
          {
            "ResponseParameters": {
              "method.response.header.Access-Control-Allow-Origin": true
            },
            "ResponseModels": {},
            "StatusCode": 200
          },
          {
            "ResponseParameters": {
              "method.response.header.Access-Control-Allow-Origin": true
            },
            "ResponseModels": {},
            "StatusCode": 400
          },
          {
            "ResponseParameters": {
              "method.response.header.Access-Control-Allow-Origin": true
            },
            "ResponseModels": {},
            "StatusCode": 401
          },
          {
            "ResponseParameters": {
              "method.response.header.Access-Control-Allow-Origin": true
            },
            "ResponseModels": {},
            "StatusCode": 403
          },
          {
            "ResponseParameters": {
              "method.response.header.Access-Control-Allow-Origin": true
            },
            "ResponseModels": {},
            "StatusCode": 404
          },
          {
            "ResponseParameters": {
              "method.response.header.Access-Control-Allow-Origin": true
            },
            "ResponseModels": {},
            "StatusCode": 422
          },
          {
            "ResponseParameters": {
              "method.response.header.Access-Control-Allow-Origin": true
            },
            "ResponseModels": {},
            "StatusCode": 500
          },
          {
            "ResponseParameters": {
              "method.response.header.Access-Control-Allow-Origin": true
            },
            "ResponseModels": {},
            "StatusCode": 502
          },
          {
            "ResponseParameters": {
              "method.response.header.Access-Control-Allow-Origin": true
            },
            "ResponseModels": {},
            "StatusCode": 504
          }
        ]
      }
    },
    "ApiGatewayMethodBeersGet": {
      "Type": "AWS::ApiGateway::Method",
      "Properties": {
        "HttpMethod": "GET",
        "RequestParameters": {},
        "ResourceId": {
          "Ref": "ApiGatewayResourceBeers"
        },
        "RestApiId": {
          "Ref": "ApiGatewayRestApi"
        },
        "AuthorizationType": "NONE",
        "Integration": {
          "IntegrationHttpMethod": "POST",
          "Type": "AWS",
          "Uri": {
            "Fn::Join": [
              "",
              [
                "arn:aws:apigateway:",
                {
                  "Ref": "AWS::Region"
                },
                ":lambda:path/2015-03-31/functions/",
                {
                  "Fn::GetAtt": [
                    "GetAllLambdaFunction",
                    "Arn"
                  ]
                },
                "/invocations"
              ]
            ]
          },
          "PassthroughBehavior": "NEVER",
          "RequestTemplates": {
            "application/json": "\n    #set( $body = $input.json(\"$\") )\n\n    \n  #define( $loop )\n    {\n    #foreach($key in $map.keySet())\n        #set( $k = $util.escapeJavaScript($key) )\n        #set( $v = $util.escapeJavaScript($map.get($key)).replaceAll(\"\\\\'\", \"'\") )\n        \"$k\":\n          \"$v\"\n          #if( $foreach.hasNext ) , #end\n    #end\n    }\n  #end\n\n  {\n    \"body\": $body,\n    \"method\": \"$context.httpMethod\",\n    \"principalId\": \"$context.authorizer.principalId\",\n    \"stage\": \"$context.stage\",\n\n    \"cognitoPoolClaims\" : {\n       \n       \"sub\": \"$context.authorizer.claims.sub\"\n    },\n\n    #set( $map = $input.params().header )\n    \"headers\": $loop,\n\n    #set( $map = $input.params().querystring )\n    \"query\": $loop,\n\n    #set( $map = $input.params().path )\n    \"path\": $loop,\n\n    #set( $map = $context.identity )\n    \"identity\": $loop,\n\n    #set( $map = $stageVariables )\n    \"stageVariables\": $loop\n  }\n\n  ",
            "application/x-www-form-urlencoded": "\n    #define( $body )\n      {\n      #foreach( $token in $input.path('$').split('&') )\n        #set( $keyVal = $token.split('=') )\n        #set( $keyValSize = $keyVal.size() )\n        #if( $keyValSize >= 1 )\n          #set( $key = $util.escapeJavaScript($util.urlDecode($keyVal[0])) )\n          #if( $keyValSize >= 2 )\n            #set($val = $util.escapeJavaScript($util.urlDecode($keyVal[1])).replaceAll(\"\\\\'\",\"'\"))\n          #else\n            #set( $val = '' )\n          #end\n          \"$key\": \"$val\"#if($foreach.hasNext),#end\n        #end\n      #end\n      }\n    #end\n\n    \n  #define( $loop )\n    {\n    #foreach($key in $map.keySet())\n        #set( $k = $util.escapeJavaScript($key) )\n        #set( $v = $util.escapeJavaScript($map.get($key)).replaceAll(\"\\\\'\", \"'\") )\n        \"$k\":\n          \"$v\"\n          #if( $foreach.hasNext ) , #end\n    #end\n    }\n  #end\n\n  {\n    \"body\": $body,\n    \"method\": \"$context.httpMethod\",\n    \"principalId\": \"$context.authorizer.principalId\",\n    \"stage\": \"$context.stage\",\n\n    \"cognitoPoolClaims\" : {\n       \n       \"sub\": \"$context.authorizer.claims.sub\"\n    },\n\n    #set( $map = $input.params().header )\n    \"headers\": $loop,\n\n    #set( $map = $input.params().querystring )\n    \"query\": $loop,\n\n    #set( $map = $input.params().path )\n    \"path\": $loop,\n\n    #set( $map = $context.identity )\n    \"identity\": $loop,\n\n    #set( $map = $stageVariables )\n    \"stageVariables\": $loop\n  }\n\n  "
          },
          "IntegrationResponses": [
            {
              "StatusCode": 200,
              "SelectionPattern": "",
              "ResponseParameters": {
                "method.response.header.Access-Control-Allow-Origin": "'*'"
              },
              "ResponseTemplates": {}
            },
            {
              "StatusCode": 400,
              "SelectionPattern": "[\\s\\S]*\\[400\\][\\s\\S]*",
              "ResponseParameters": {
                "method.response.header.Access-Control-Allow-Origin": "'*'"
              },
              "ResponseTemplates": {}
            },
            {
              "StatusCode": 401,
              "SelectionPattern": "[\\s\\S]*\\[401\\][\\s\\S]*",
              "ResponseParameters": {
                "method.response.header.Access-Control-Allow-Origin": "'*'"
              },
              "ResponseTemplates": {}
            },
            {
              "StatusCode": 403,
              "SelectionPattern": "[\\s\\S]*\\[403\\][\\s\\S]*",
              "ResponseParameters": {
                "method.response.header.Access-Control-Allow-Origin": "'*'"
              },
              "ResponseTemplates": {}
            },
            {
              "StatusCode": 404,
              "SelectionPattern": "[\\s\\S]*\\[404\\][\\s\\S]*",
              "ResponseParameters": {
                "method.response.header.Access-Control-Allow-Origin": "'*'"
              },
              "ResponseTemplates": {}
            },
            {
              "StatusCode": 422,
              "SelectionPattern": "[\\s\\S]*\\[422\\][\\s\\S]*",
              "ResponseParameters": {
                "method.response.header.Access-Control-Allow-Origin": "'*'"
              },
              "ResponseTemplates": {}
            },
            {
              "StatusCode": 500,
              "SelectionPattern": "[\\s\\S]*(Process\\s?exited\\s?before\\s?completing\\s?request|\\[500\\])[\\s\\S]*",
              "ResponseParameters": {
                "method.response.header.Access-Control-Allow-Origin": "'*'"
              },
              "ResponseTemplates": {}
            },
            {
              "StatusCode": 502,
              "SelectionPattern": "[\\s\\S]*\\[502\\][\\s\\S]*",
              "ResponseParameters": {
                "method.response.header.Access-Control-Allow-Origin": "'*'"
              },
              "ResponseTemplates": {}
            },
            {
              "StatusCode": 504,
              "SelectionPattern": "[\\s\\S]*\\[504\\][\\s\\S]*",
              "ResponseParameters": {
                "method.response.header.Access-Control-Allow-Origin": "'*'"
              },
              "ResponseTemplates": {}
            }
          ]
        },
        "MethodResponses": [
          {
            "ResponseParameters": {
              "method.response.header.Access-Control-Allow-Origin": true
            },
            "ResponseModels": {},
            "StatusCode": 200
          },
          {
            "ResponseParameters": {
              "method.response.header.Access-Control-Allow-Origin": true
            },
            "ResponseModels": {},
            "StatusCode": 400
          },
          {
            "ResponseParameters": {
              "method.response.header.Access-Control-Allow-Origin": true
            },
            "ResponseModels": {},
            "StatusCode": 401
          },
          {
            "ResponseParameters": {
              "method.response.header.Access-Control-Allow-Origin": true
            },
            "ResponseModels": {},
            "StatusCode": 403
          },
          {
            "ResponseParameters": {
              "method.response.header.Access-Control-Allow-Origin": true
            },
            "ResponseModels": {},
            "StatusCode": 404
          },
          {
            "ResponseParameters": {
              "method.response.header.Access-Control-Allow-Origin": true
            },
            "ResponseModels": {},
            "StatusCode": 422
          },
          {
            "ResponseParameters": {
              "method.response.header.Access-Control-Allow-Origin": true
            },
            "ResponseModels": {},
            "StatusCode": 500
          },
          {
            "ResponseParameters": {
              "method.response.header.Access-Control-Allow-Origin": true
            },
            "ResponseModels": {},
            "StatusCode": 502
          },
          {
            "ResponseParameters": {
              "method.response.header.Access-Control-Allow-Origin": true
            },
            "ResponseModels": {},
            "StatusCode": 504
          }
        ]
      }
    },
    "ApiGatewayDeployment1486874552929": {
      "Type": "AWS::ApiGateway::Deployment",
      "Properties": {
        "RestApiId": {
          "Ref": "ApiGatewayRestApi"
        },
        "StageName": "v2"
      },
      "DependsOn": [
        "ApiGatewayMethodBeersIdVarGet",
        "ApiGatewayMethodBeersGet"
      ]
    },
    "GetOneLambdaPermissionApiGateway": {
      "Type": "AWS::Lambda::Permission",
      "Properties": {
        "FunctionName": {
          "Fn::GetAtt": [
            "GetOneLambdaFunction",
            "Arn"
          ]
        },
        "Action": "lambda:InvokeFunction",
        "Principal": "apigateway.amazonaws.com",
        "SourceArn": {
          "Fn::Join": [
            "",
            [
              "arn:aws:execute-api:",
              {
                "Ref": "AWS::Region"
              },
              ":",
              {
                "Ref": "AWS::AccountId"
              },
              ":",
              {
                "Ref": "ApiGatewayRestApi"
              },
              "/*/*"
            ]
          ]
        }
      }
    },
    "GetAllLambdaPermissionApiGateway": {
      "Type": "AWS::Lambda::Permission",
      "Properties": {
        "FunctionName": {
          "Fn::GetAtt": [
            "GetAllLambdaFunction",
            "Arn"
          ]
        },
        "Action": "lambda:InvokeFunction",
        "Principal": "apigateway.amazonaws.com",
        "SourceArn": {
          "Fn::Join": [
            "",
            [
              "arn:aws:execute-api:",
              {
                "Ref": "AWS::Region"
              },
              ":",
              {
                "Ref": "AWS::AccountId"
              },
              ":",
              {
                "Ref": "ApiGatewayRestApi"
              },
              "/*/*"
            ]
          ]
        }
      }
    }
  },
  "Outputs": {
    "ServerlessDeploymentBucketName": {
      "Value": {
        "Ref": "ServerlessDeploymentBucket"
      }
    },
    "GetOneLambdaFunctionQualifiedArn": {
      "Description": "Current Lambda function version",
      "Value": {
        "Ref": "GetOneLambdaVersiongANkUULSFXTVajACJsDneWX2es5dPpVH6Bg9mI09v8"
      }
    },
    "GetAllLambdaFunctionQualifiedArn": {
      "Description": "Current Lambda function version",
      "Value": {
        "Ref": "GetAllLambdaVersionuBh2QCn69uklMiYyK6fY9eqy6CMAgXSCqKY889rug"
      }
    },
    "ServiceEndpoint": {
      "Description": "URL of the service endpoint",
      "Value": {
        "Fn::Join": [
          "",
          [
            "https://",
            {
              "Ref": "ApiGatewayRestApi"
            },
            ".execute-api.us-west-1.amazonaws.com/v2"
          ]
        ]
      }
    }
  }
}